parsimonious_lite/__init__.py
parsimonious_lite/exceptions.py
parsimonious_lite/expressions.py
parsimonious_lite/grammar.py
parsimonious_lite/nodes.py
parsimonious_lite/utils.py
parsimonious_lite/tests/__init__.py
parsimonious_lite/tests/benchmarks.py
parsimonious_lite/tests/test_benchmarks.py
parsimonious_lite/tests/test_expressions.py
parsimonious_lite/tests/test_grammar.py
parsimonious_lite/tests/test_nodes.py
parsimonious_lite-0.11.0.dist-info/LICENSE
parsimonious_lite-0.11.0.dist-info/METADATA
parsimonious_lite-0.11.0.dist-info/WHEEL
parsimonious_lite-0.11.0.dist-info/top_level.txt
parsimonious_lite-0.11.0.dist-info/RECORD
